wink_sdk_affiliate_sales_channel/__init__.py
wink_sdk_affiliate_sales_channel/api_client.py
wink_sdk_affiliate_sales_channel/api_response.py
wink_sdk_affiliate_sales_channel/configuration.py
wink_sdk_affiliate_sales_channel/exceptions.py
wink_sdk_affiliate_sales_channel/py.typed
wink_sdk_affiliate_sales_channel/rest.py
wink_sdk_affiliate_sales_channel/api/__init__.py
wink_sdk_affiliate_sales_channel/api/affiliate_api.py
wink_sdk_affiliate_sales_channel/api/available_supplier_api.py
wink_sdk_affiliate_sales_channel/api/relationship_request_api.py
wink_sdk_affiliate_sales_channel/api/sales_channel_api.py
wink_sdk_affiliate_sales_channel/models/__init__.py
wink_sdk_affiliate_sales_channel/models/address_affiliate.py
wink_sdk_affiliate_sales_channel/models/aggregate_descriptor_affiliate.py
wink_sdk_affiliate_sales_channel/models/browse_suppliers400_response.py
wink_sdk_affiliate_sales_channel/models/composite_filter_descriptor_affiliate.py
wink_sdk_affiliate_sales_channel/models/contact_affiliate.py
wink_sdk_affiliate_sales_channel/models/country_affiliate.py
wink_sdk_affiliate_sales_channel/models/custom_monetary_amount.py
wink_sdk_affiliate_sales_channel/models/filter_descriptor_affiliate.py
wink_sdk_affiliate_sales_channel/models/general_manager_affiliate.py
wink_sdk_affiliate_sales_channel/models/generic_error_message.py
wink_sdk_affiliate_sales_channel/models/geo_json_point_affiliate.py
wink_sdk_affiliate_sales_channel/models/geo_name_affiliate.py
wink_sdk_affiliate_sales_channel/models/group_descriptor_affiliate.py
wink_sdk_affiliate_sales_channel/models/hotel_on_map_affiliate.py
wink_sdk_affiliate_sales_channel/models/hotel_on_map_view_affiliate.py
wink_sdk_affiliate_sales_channel/models/image_attribution_affiliate.py
wink_sdk_affiliate_sales_channel/models/key_value_pair_affiliate.py
wink_sdk_affiliate_sales_channel/models/localized_description_affiliate.py
wink_sdk_affiliate_sales_channel/models/media_author_attribution_affiliate.py
wink_sdk_affiliate_sales_channel-0.0.57.dist-info/licenses/LICENSE
wink_sdk_affiliate_sales_channel-0.0.57.dist-info/METADATA
wink_sdk_affiliate_sales_channel-0.0.57.dist-info/WHEEL
wink_sdk_affiliate_sales_channel-0.0.57.dist-info/top_level.txt
wink_sdk_affiliate_sales_channel-0.0.57.dist-info/RECORD
